xdtools/__init__.py
xdtools/artboard.py
xdtools/xdfile.py
xdtools/artwork/__init__.py
xdtools/artwork/artwork.py
xdtools/artwork/compound.py
xdtools/artwork/ellipse.py
xdtools/artwork/group.py
xdtools/artwork/line.py
xdtools/artwork/path.py
xdtools/artwork/rectangle.py
xdtools/artwork/text.py
xdtools/style/__init__.py
xdtools/style/blur.py
xdtools/style/color_fill.py
xdtools/style/color_stroke.py
xdtools/style/drop_shadow.py
xdtools/style/fill.py
xdtools/style/filter.py
xdtools/style/font.py
xdtools/style/gradient_fill.py
xdtools/style/opacity.py
xdtools/style/pattern_fill.py
xdtools/style/stroke.py
xdtools/style/style.py
xdtools/style/text_attributes.py
xdtools/utils/__init__.py
xdtools/utils/clip_path.py
xdtools/utils/color.py
xdtools/utils/exceptions.py
xdtools/utils/gradient.py
xdtools/utils/parser.py
xdtools/utils/point.py
xdtools-0.0.8.dist-info/DESCRIPTION.rst
xdtools-0.0.8.dist-info/METADATA
xdtools-0.0.8.dist-info/RECORD
xdtools-0.0.8.dist-info/WHEEL
xdtools-0.0.8.dist-info/metadata.json
xdtools-0.0.8.dist-info/top_level.txt
