Metadata-Version: 2.0
Name: xdtools
Version: 0.0.8
Summary: An unofficial Python API for Adobe Experience Design
Home-page: https://github.com/umar-ahmed/xdtools
Author: Umar Ahmed
Author-email: umar.ahmed@mail.utoronto.ca
License: MIT
Download-URL: https://github.com/umar-ahmed/xdtools/archive/0.0.8.tar.gz
Keywords: adobe,xd,ui,ux
Platform: UNKNOWN
